mpb/__init__.py
mpb/mpb.py
ppl/__init__.py
ppl/ppl.py
ppl-0.2.0.dist-info/METADATA
ppl-0.2.0.dist-info/RECORD
ppl-0.2.0.dist-info/WHEEL
ppl-0.2.0.dist-info/top_level.txt
